onlyforfun/__init__.py
onlyforfun-0.4.dist-info/DESCRIPTION.rst
onlyforfun-0.4.dist-info/METADATA
onlyforfun-0.4.dist-info/RECORD
onlyforfun-0.4.dist-info/WHEEL
onlyforfun-0.4.dist-info/metadata.json
onlyforfun-0.4.dist-info/top_level.txt
