Metadata-Version: 2.0
Name: onlyforfun
Version: 0.4
Summary: Addition methods for test purpose
Home-page: https://github.com/sigdelsanjog/onlyforfun
Author: Fun Maker
Author-email: flyingcircus@example.com
License: MIT
Platform: UNKNOWN
